{"cameraMode":{"drawMode":0,"name":"Shaded","section":"Shading Mode"},"sceneLighting":true,"audioPlay":false,"sceneViewState":{"showFog":true,"showMaterialUpdate":false,"showSkybox":true,"showFlares":true,"showImageEffects":true,"showParticleSystems":true,"showVisualEffectGraphs":true,"m_FxEnabled":true},"in2DMode":false,"pivot":{"x":3.044959306716919,"y":-27.901044845581056,"z":21.657400131225587},"rotation":{"x":0.43425825238227847,"y":0.06260112673044205,"z":-0.03043513186275959,"w":0.8982978463172913},"size":22.9852294921875,"orthographic":false}